{
  "appId": "com.cleansomething.app",
  "appName": "CSFN",
  "bundledWebRuntime": false,
  "npmClient": "npm",
  "webDir": "dist",
  "backgroundColor": "#ffffffff",
  "server": {
    "hostname": "native.cleansomethingfornothing.com"
  },
  "plugins": {
    "SplashScreen": {
      "launchShowDuration": 10000,
      "splashFullScreen": false,
      "splashImmersive": false
    },
    "GoogleAuth": {
      "scopes": [
        "profile",
        "email"
      ],
      "serverClientId": "597121035718-js77umaebmsjp5c9qbvjvc9oee4o1e85.apps.googleusercontent.com",
      "forceCodeForRefreshToken": true
    },
    "Keyboard": {
      "resize": "none"
    }
  }
}
